dnv/__init__.py
dnv/sesam/__init__.py
dnv/sesam/sifapi/__init__.py
dnv/sesam/sifapi/.dlls/DNV.Sesam.Sif.Decoder.dll
dnv/sesam/sifapi/.dlls/DNV.Sesam.Sif.FiniteElement.Helper.dll
dnv/sesam/sifapi/.dlls/DNV.Sesam.SifApi.Core.dll
dnv/sesam/sifapi/.dlls/DNV.Sesam.SifApi.DataTypes.dll
dnv/sesam/sifapi/.dlls/DNV.Sesam.SifApi.IO.dll
dnv/sesam/sifapi/.dlls/MathNet.Numerics.dll
dnv/sesam/sifapi/.dlls/QuantityTypes.dll
dnv/sesam/sifapi/.dlls/SifIO.dll
dnv/sesam/sifapi/.dlls/System.Text.Json.dll
dnv/sesam/sifapi/.dlls/csFastFloat.dll
dnv/sesam/sifapi/core/__init__.py
dnv/sesam/sifapi/core/__init__.pyi
dnv/sesam/sifapi/datatypes/__init__.py
dnv/sesam/sifapi/datatypes/__init__.pyi
dnv/sesam/sifapi/datatypes/helpers/__init__.py
dnv/sesam/sifapi/datatypes/helpers/__init__.pyi
dnv/sesam/sifapi/io/__init__.py
dnv/sesam/sifapi/io/__init__.pyi
dnv_sifio-5.3.6.dist-info/LICENSE
dnv_sifio-5.3.6.dist-info/METADATA
dnv_sifio-5.3.6.dist-info/WHEEL
dnv_sifio-5.3.6.dist-info/top_level.txt
dnv_sifio-5.3.6.dist-info/RECORD
