Metadata-Version: 2.1
Name: dnv-sifio
Version: 5.3.6
Summary: SifIO is a Python package for reading and writing access of SIF data types to Sesam Interface Files.
Author-email: DNV AS <software.support@dnv.com>
License: MIT License
Project-URL: Homepage, https://sesam.dnv.com/download/api/sifio/index.html
Keywords: sesam,sif,sifio
Classifier: License :: OSI Approved :: MIT License
Classifier: Programming Language :: Python
Classifier: Programming Language :: Python :: 3.10
Classifier: Programming Language :: Python :: 3.11
Classifier: Programming Language :: Python :: 3.12
Requires-Python: >=3.10
License-File: LICENSE
Requires-Dist: pythonnet ==3.0.3
